{
	"projectid": "1108100302_test1",
	"setting": {
		"urlCheck": true,
		"es6": true,
		"postcss": true,
		"minified": true,
		"newFeature": true,
		"autoAudits": false
	},
	"qqLibVersion": "1.4.8",
	"compileType": "miniprogram",
	"createTime": 1562750155128,
	"accessTime": 1562750155128,
	"packOptions": {
		"ignore": []
	},
	"debugOptions": {
		"hidedInDevtools": []
	},
	"qqappid": "1109745470",
	"projectname": "test1",
	"condition": {
		"search": {
			"current": -1,
			"list": []
		},
		"conversation": {
			"current": -1,
			"list": []
		},
		"game": {
			"currentL": -1,
			"list": []
		},
		"miniprogram": {
			"current": -1,
			"list": []
		}
	}
}